mongo_validations_generator/__init__.py
mongo_validations_generator/bson_type.py
mongo_validations_generator/conftest.py
mongo_validations_generator/core.py
mongo_validations_generator/custom_types.py
mongo_validations_generator/py.typed
mongo_validations_generator/schema.py
mongo_validations_generator-1.2.0.dist-info/METADATA
mongo_validations_generator-1.2.0.dist-info/WHEEL
mongo_validations_generator-1.2.0.dist-info/licenses/LICENSE
mongo_validations_generator-1.2.0.dist-info/RECORD
