Metadata-Version: 2.4
Name: mongo-validations-generator
Version: 1.2.0
Summary: Generate MongoDB validation schemas from Python type annotations and Pydantic models.
Project-URL: Homepage, https://github.com/all-win-solutions/mongo-validations-generator
Project-URL: Repository, https://github.com/all-win-solutions/mongo-validations-generator
Project-URL: Issues, https://github.com/all-win-solutions/mongo-validations-generator/issues
Project-URL: Changelog, https://github.com/all-win-solutions/mongo-validations-generator/blob/main/CHANGELOG.md
Author-email: Alejandro Castillo <alejandro@all-win.software>
License: BSD-3-Clause
License-File: LICENSE
Classifier: Intended Audience :: Developers
Classifier: License :: OSI Approved :: BSD License
Classifier: Operating System :: OS Independent
Classifier: Programming Language :: Python
Classifier: Programming Language :: Python :: 3.12
Classifier: Topic :: Database :: Front-Ends
Classifier: Topic :: Software Development :: Libraries :: Python Modules
Classifier: Typing :: Typed
Requires-Python: >=3.12
Requires-Dist: pydantic>=2.10.6
Requires-Dist: pymongo>=4.11.3
